arcternweb/__init__.py
arcternweb/client.py
arcternweb/exceptions.py
arcternweb/models/__init__.py
arcternweb/models/common.py
arcternweb/models/infer_task.py
arcternweb/models/model_group.py
arcternweb/services/__init__.py
arcternweb/services/classifier.py
arcternweb/services/infer_task.py
arcternweb/services/model_group.py
arcternweb/services/utils.py
arcternweb/utils/__init__.py
arcternweb/utils/di.py
arcternweb/utils/download.py
arcternweb/utils/http.py
arcternweb/utils/s3.py
intellif_arcternweb-0.0.1.dist-info/licenses/LICENSE
intellif_arcternweb-0.0.1.dist-info/METADATA
intellif_arcternweb-0.0.1.dist-info/WHEEL
intellif_arcternweb-0.0.1.dist-info/top_level.txt
intellif_arcternweb-0.0.1.dist-info/RECORD
