Metadata-Version: 2.4
Name: intellif-arcternweb
Version: 0.0.1
Summary: Intellif ArcternWeb SDK.
Author-email: Platform Team <arcternweb@example.com>
License-Expression: Apache-2.0
Keywords: ArcternWeb,sdk,intellif
Classifier: Programming Language :: Python :: 3
Classifier: Operating System :: OS Independent
Requires-Python: >=3.9
License-File: LICENSE
Requires-Dist: httpx<0.28,>=0.27
Requires-Dist: pydantic<3.0,>=2.5.3
Requires-Dist: typing-extensions<5.0,>=4.13.2
Requires-Dist: pyarrow>=21.0.0
Requires-Dist: tqdm<5.0,>=4.66
Requires-Dist: loguru>=0.7.3
Requires-Dist: minio>=7.2.7
Requires-Dist: requests>=2.32.4
Dynamic: license-file
